PythonReact/__init__.py
PythonReact/console.py
pythonreact-0.2.dist-info/LICENSE
pythonreact-0.2.dist-info/METADATA
pythonreact-0.2.dist-info/WHEEL
pythonreact-0.2.dist-info/top_level.txt
pythonreact-0.2.dist-info/RECORD
