Metadata-Version: 2.1
Name: pythonreact
Version: 0.2
Summary: A react type module for nice visuals in the console
Home-page: https://github.com/donkere-vader/picodoc
Author: Donkere Vader
Author-email: donkere.v@gmail.com
License: UNKNOWN
Project-URL: Bug Tracker, https://github.com/donkere-vader/picodoc/issues
Platform: UNKNOWN
Classifier: Programming Language :: Python :: 3
Classifier: License :: OSI Approved :: MIT License
Classifier: Operating System :: OS Independent
Requires-Python: >=3.8
License-File: LICENSE
Requires-Dist: rich (>=10.3.0)
